{
  "title": "Heavy Metal",
  "description": "Heavy metal (often referred to simply as metal) is a genre of rock music that developed in the late 1960s and early 1970s, largely in the United Kingdom and the United States. With roots in blues-rock and psychedelic rock, the bands that created heavy metal developed a thick, massive sound, characterized by highly amplified distortion, extended guitar solos, emphatic beats, and overall loudness. Heavy metal lyrics and performance styles are generally associated with masculinity and machismo.\n<br><br>\nIn the late 1960s the term heavy metal was used interchangeably with hard rock, but gradually began to be used to describe music played with even more volume and intensity. While hard rock maintained a bluesy rock and roll identity, including some swing in the back beat and riffs that tended to outline chord progressions in their hooks, heavy metal's riffs often functioned as stand-alone melodies and had no swing in them.\n<br><br>\nLed Zeppelin defined central aspects of the emerging genre, with Page's highly distorted guitar style and singer Robert Plant's dramatic, wailing vocals. Other bands, with a more consistently heavy, \"purely\" metal sound, would prove equally important in codifying the genre. The 1970 releases by Black Sabbath (Black Sabbath and Paranoid) were crucial in this regard. Black Sabbath had developed a particularly heavy sound in part due to an industrial accident guitarist Tony Iommi suffered before cofounding the band. Unable to play normally, Iommi had to tune his guitar down for easier fretting and rely on power chords with their relatively simple fingering. Deep Purple had fluctuated between styles in its early years, but by 1969 vocalist Ian Gillan and guitarist Ritchie Blackmore had led the band toward the developing heavy metal style.\n<br><br>\nJudas Priest arrived to unify and amplify the heavy metal aesthetic from hard rock's sonic palette. For the first time, heavy metal became a true genre unto itself. Though Judas Priest did not have a top 40 album in the U.S. until 1980, for many it was the definitive post-Sabbath heavy metal band; its twin-guitar attack, featuring rapid tempos and a nonbluesy, more cleanly metallic sound, was a major influence on later acts.\n<br><br>\nMany subgenres of heavy metal developed outside of the commercial mainstream during and after the 1980s.\n<br>\n<a href=\"http://en.wikipedia.org/wiki/Heavy_metal_music\" target=\"_blank\">(Source)</a>",
  "tracklist": [
    {
      "artist": "Black Sabbath",
      "title": "Black Sabbath",
      "year": "1970",
      "videos": [
        "2KnyL4IFcwo",
        "0lVdMbUx1_k",
        "qrVKmTPFYZ8",
        "OhhOU5FUPBE",
        "hV2ideRjDIk",
        "0qanF-91aJo"
      ]
    },
    {
      "artist": "Black Sabbath",
      "title": "Paranoid",
      "year": "1970",
      "videos": [
        "hkXHsK4AQPs",
        "cNdB5-A9O7g",
        "Uq42HUUJFzU",
        "vi2nxSxbSQI",
        "oz079ax0PKY",
        "BIlPLCc0WnA"
      ]
    },
    {
      "artist": "Black Sabbath",
      "title": "War Pigs",
      "year": "1970",
      "videos": [
        "pZCyOWLrRTE",
        "LQUXuQ6Zd9w",
        "XMawlzqJHg8",
        "0GRR_n_yQGA",
        "K3b6SGoN6dA",
        "sG0nEgigoa0",
        "uJ6QHfZwTSw"
      ]
    },
    {
      "artist": "Black Sabbath",
      "title": "Iron Man",
      "year": "1970",
      "videos": [
        "9LjbMVXj0F8",
        "5s7_WbiR79E",
        "jNo3zmhXE9Y",
        "8aQRq9hhekA",
        "Uctu1e353os",
        "yp-2CHFjKUI",
        "26WIVsf1Y_c"
      ]
    },
    {
      "artist": "Sir Lord Baltimore",
      "title": "Caesar Lxxi",
      "year": "1971",
      "videos": [
        "h62zNXXkruE",
        "RADygP0hWNU",
        "HwzkyH-deVw",
        "hCZ0kumeGgg",
        "TfSBambFx8E",
        "5vRKTAAo-24",
        "TkdPTs75LoE"
      ]
    },
    {
      "artist": "Black Sabbath",
      "title": "Children Of The Grave",
      "year": "1971",
      "videos": [
        "fl4M0Ulbk9A",
        "2ISstl_2zjk",
        "X7UZeHvMYZA",
        "p06tGyel3TE",
        "4AzY6vFLiuY",
        "U39EiI-NR4I",
        "-_USYaYhACc"
      ]
    },
    {
      "artist": "Black Sabbath",
      "title": "Sabbath Bloody Sabbath",
      "year": "1973",
      "videos": [
        "ReuBms-qZQk",
        "mfTpjrzas5E",
        "G8305fgmzGU",
        "XNfBxPmr3cg",
        "RW68zUxqsqM",
        "wJ4cHa4PFpo",
        "5KXg8JMJmig"
      ]
    },
    {
      "artist": "Budgie",
      "title": "Breadfan",
      "year": "1973",
      "videos": [
        "s3-l_T6AuNk",
        "orYr_dVnb48",
        "wi25hHnU-8g",
        "axAE1Oh2H14",
        "GUI3hxV0d8o",
        "uDQJZeCobIQ"
      ]
    },
    {
      "artist": "Buffalo",
      "title": "Shylock",
      "year": "1973",
      "videos": [
        "at7JvfvMB5c",
        "LHKMH5aL4bE",
        "bkdI-mZ5nYE",
        "ihRZaw8W3ks",
        "3N2c1Zwd4ao",
        "EUiOBNvULzE"
      ]
    },
    {
      "artist": "Queen",
      "title": "Stone Cold Crazy",
      "year": "1974",
      "videos": [
        "Mmt2mgmrSUw",
        "S0kTkxhyWNo",
        "AnGaEk0rZdU",
        "7EvJ4y-zpwM",
        "gY05WFFvovU",
        "dYkT_eoZSWU",
        "i8g3-innzCM"
      ]
    },
    {
      "artist": "Judas Priest",
      "title": "Never Satisfied (Live)",
      "year": "1974",
      "videos": [
        "aJMmF1h-RHo",
        "5EVpdv4Zb-0",
        "MvLmpXXPDB8",
        "M6puEXQy6tE",
        "I66kB5tvwyE",
        "RHdvSUAo1BY",
        "SiV2-nXEzus"
      ]
    },
    {
      "artist": "Scorpions",
      "title": "Dark Lady",
      "year": "1975",
      "videos": [
        "kWwBKkEQEVM",
        "D0lcY0Jxa0U",
        "Z_36fjL5Z84",
        "qdBOnTjTpoI",
        "y1Ytc4w_Iv8",
        "QL4Yr8ZKr9Q",
        "SNzcLXq5Hi0"
      ]
    },
    {
      "artist": "Judas Priest",
      "title": "Victim Of Changes",
      "year": "1976",
      "videos": [
        "EKSU1W0ZUmQ",
        "hDzutIb6p6I",
        "J4d5sMg8eCE",
        "HQnTv1Kghcg",
        "PYcN8tN4P3Y",
        "M7HyXx92Dmo"
      ]
    },
    {
      "artist": "Judas Priest",
      "title": "The Ripper",
      "year": "1976",
      "videos": [
        "VfGClVJh0zk",
        "lriWlHZAy8A",
        "mJfMBxG0dyk",
        "coLvuP7hQCA",
        "JDw7G5nxtfA",
        "aAychCCuDiY",
        "UbMFhI_GSFs"
      ]
    },
    {
      "artist": "Judas Priest",
      "title": "Dissident Agressor",
      "year": "1977",
      "videos": [
        "H_mpt8xyZVI",
        "Gjsn7aLPgCM",
        "cEvDlivJeVo",
        "VZOb45FNxvo",
        "yxoI7Jtqw5Y",
        "VlCu1QvntSU"
      ]
    },
    {
      "artist": "Judas Priest",
      "title": "Savage",
      "year": "1978",
      "videos": [
        "qIU5vgfop8g",
        "mSIQV-YeSIw",
        "gTiXP-n-frQ",
        "YOiIJyp36AU",
        "EnQv15B8qcg",
        "fnUaq1YGUns"
      ]
    },
    {
      "artist": "Judas Priest",
      "title": "Stained Class",
      "year": "1978",
      "videos": [
        "ciECUVrklZc",
        "kPVhllP82yc",
        "65LHTBVGFyE",
        "2Ox73Iu0vFE",
        "WfhskiCdAzU",
        "yE0YKx97Aes",
        "z44z-knCLf8"
      ]
    },
    {
      "artist": "Motorhead",
      "title": "Ace Of Spades",
      "year": "1980",
      "videos": [
        "aSsqavYIgNc",
        "pWB5JZRGl0U",
        "HpwUTJsI3xI",
        "aVecmhNYbuQ",
        "vcf7DnHi54g",
        "hirZFmRwXvE",
        "co9yv2NjyWs"
      ]
    },
    {
      "artist": "Motorhead",
      "title": "We Are The Road Crew",
      "year": "1980",
      "videos": [
        "DdhfCIbrRy8",
        "H71VEV1c_XE",
        "BmhhVgCD0hg",
        "fb3zSgxMuug",
        "1FtVR7gdp5c",
        "fnVh0Ptq93k",
        "MQ9V5cRSOPg"
      ]
    },
    {
      "artist": "Black Sabbath",
      "title": "Neon Knights",
      "year": "1980",
      "videos": [
        "zTgj0KUpGhU",
        "YF3jeAPGhrY",
        "HF1SEMEp_BY",
        "nhe1SuBGkiA",
        "oFSCleamr-0",
        "Jn-5-9-V1k0",
        "qhnhKalkmk4"
      ]
    },
    {
      "artist": "Ozzy Osbourne",
      "title": "Diary Of A Madman",
      "year": "1981",
      "videos": [
        "WiEJOzAVAXc",
        "Pbpw_MS-bJg",
        "nZ5_KQcou-I",
        "ApTX0n6gIzE",
        "bnNWUUZ7cEA",
        "PKzwPX-aIj0",
        "vb7PY8Xfg98"
      ]
    },
    {
      "artist": "Black Sabbath",
      "title": "Mob Rules",
      "year": "1981",
      "videos": [
        "owJJQgt_jgs",
        "oO6uBQJ35N0",
        "8naVYRCT6Eg",
        "Zxt6yFBi4Ao",
        "c9yZtsZzBkY",
        "Z-NaGuyM5Wo"
      ]
    },
    {
      "artist": "Judas Priest",
      "title": "Electric Eye",
      "year": "1982",
      "videos": [
        "EQ96oEwYrE8",
        "yMVV_HsHcX0",
        "BEfOGyvyfFY",
        "oCvRlD51JyI",
        "nmji9imoCjI",
        "b1B_pZC8aWU",
        "UMJF37BVGTA"
      ]
    },
    {
      "artist": "Mercyful Fate",
      "title": "Evil",
      "year": "1983",
      "videos": [
        "Rro2sq2Zmd0",
        "ZWqBm28ZKeE",
        "nZ6s89QWYjc",
        "ZWWsVqi4sZQ",
        "emdQZBDmNEY",
        "jn9i6Uv3ewA",
        "OXwQ2XWMNuM"
      ]
    },
    {
      "artist": "Motorhead",
      "title": "Back At The Funny Farm",
      "year": "1983",
      "videos": [
        "q4wMn21DePs",
        "fFZhfysKcyg",
        "gIPGVztoCuY",
        "vpQ2T8cpqDo",
        "LoSsF0hJydI",
        "7ztjO-RtuMQ"
      ]
    },
    {
      "artist": "Dio",
      "title": "Holy Diver",
      "year": "1983",
      "videos": [
        "QuVfrLh9Oz4",
        "NR7dG_m3MsI",
        "zfB6rMGWQe4",
        "EhGEGIBGLu8",
        "bkysjcs5vFU",
        "lGgVSbjqcRM",
        "BxYQo43dw00"
      ]
    },
    {
      "artist": "Mercyful Fate",
      "title": "Desecration Of Souls",
      "year": "1984",
      "videos": [
        "SXyevO_5ByQ",
        "xV7pcdzmoDY",
        "KqHVvbhAAEA",
        "kaysf7gBT80",
        "RUMUjoza_JY",
        "Nis__DuROPE",
        "tA6XMS0_nr4"
      ]
    },
    {
      "artist": "Mercyful Fate",
      "title": "A Dangerous Meeting",
      "year": "1984",
      "videos": [
        "WBQU3BDwrTI",
        "LWCOqNHzM0k",
        "PkvoB_HDt4c",
        "S501DO783Nk",
        "M62zt0CZid4",
        "-gmACVjtI6o",
        "mNugzc2VIt4"
      ]
    },
    {
      "artist": "King Diamond",
      "title": "Abigail",
      "year": "1987",
      "videos": [
        "bdJKLE58FUM",
        "U-yYG00Nr8I",
        "g9LtReyYaE0",
        "xGC2iP5ss6E",
        "-8C-cZ2U1Qc",
        "THRhrSmv0jA"
      ]
    },
    {
      "artist": "Judas Priest",
      "title": "Painkiller",
      "year": "1990",
      "videos": [
        "WS6-vI70oc0",
        "nM__lPTWThU",
        "jYYr9q9F1-E",
        "ACWM6GTcNW8",
        "UJ4Nel-aHZM",
        "I20QRK-K8ME"
      ]
    },
    {
      "artist": "Judas Priest",
      "title": "Leather Rebel",
      "year": "1990",
      "videos": [
        "oN4zTDFvJuQ",
        "bTQz1ABtzek",
        "awOyqGBOHJY",
        "rh-WzKZ1fIo",
        "X7wxOmixIgU",
        "jd0DOALHA7A"
      ]
    }
  ],
  "id": "heavymetal"
}